{
  "clicks": [
    {
      "timestamp": "2018-01-14T11:07:48.962Z",
      "x": 116,
      "y": 28,
      "id": 1
    },
    {
      "timestamp": "2018-01-14T11:07:52.945Z",
      "x": 509,
      "y": 40,
      "id": 2
    },
    {
      "timestamp": "2018-01-14T11:48:17.940Z",
      "x": 536,
      "y": 70,
      "id": 3
    },
    {
      "timestamp": "2018-01-14T11:48:37.035Z",
      "x": 368,
      "y": 76,
      "id": 4
    },
    {
      "timestamp": "2018-01-14T11:51:00.419Z",
      "x": 322,
      "y": 146,
      "id": 5
    },
    {
      "timestamp": "2018-01-14T11:51:14.291Z",
      "x": 378,
      "y": 168,
      "id": 6
    },
    {
      "timestamp": "2018-01-14T14:46:27.988Z",
      "x": 318,
      "y": 305,
      "id": 7
    },
    {
      "timestamp": "2018-01-14T14:46:30.341Z",
      "x": 445,
      "y": 237,
      "id": 8
    },
    {
      "timestamp": "2018-01-14T14:46:31.108Z",
      "x": 295,
      "y": 190,
      "id": 9
    },
    {
      "timestamp": "2018-01-14T14:46:31.572Z",
      "x": 399,
      "y": 322,
      "id": 10
    },
    {
      "timestamp": "2018-01-14T14:46:31.867Z",
      "x": 547,
      "y": 233,
      "id": 11
    },
    {
      "timestamp": "2018-01-14T14:46:32.228Z",
      "x": 431,
      "y": 186,
      "id": 12
    },
    {
      "timestamp": "2018-01-14T14:46:32.411Z",
      "x": 444,
      "y": 266,
      "id": 13
    },
    {
      "timestamp": "2018-01-14T14:46:32.563Z",
      "x": 445,
      "y": 275,
      "id": 14
    },
    {
      "timestamp": "2018-01-14T14:46:32.723Z",
      "x": 445,
      "y": 271,
      "id": 15
    },
    {
      "timestamp": "2018-01-14T14:46:32.860Z",
      "x": 446,
      "y": 271,
      "id": 16
    },
    {
      "timestamp": "2018-01-14T14:46:33.041Z",
      "x": 544,
      "y": 283,
      "id": 17
    },
    {
      "timestamp": "2018-01-14T14:46:33.429Z",
      "x": 533,
      "y": 168,
      "id": 18
    },
    {
      "timestamp": "2018-01-14T14:46:33.593Z",
      "x": 466,
      "y": 137,
      "id": 19
    },
    {
      "timestamp": "2018-01-14T14:46:33.733Z",
      "x": 372,
      "y": 133,
      "id": 20
    },
    {
      "timestamp": "2018-01-14T14:46:33.909Z",
      "x": 305,
      "y": 138,
      "id": 21
    },
    {
      "timestamp": "2018-01-14T14:46:34.045Z",
      "x": 278,
      "y": 160,
      "id": 22
    },
    {
      "timestamp": "2018-01-14T14:46:34.202Z",
      "x": 267,
      "y": 203,
      "id": 23
    },
    {
      "timestamp": "2018-01-14T14:46:34.394Z",
      "x": 271,
      "y": 268,
      "id": 24
    },
    {
      "timestamp": "2018-01-14T14:46:34.518Z",
      "x": 290,
      "y": 306,
      "id": 25
    },
    {
      "timestamp": "2018-01-14T14:46:34.633Z",
      "x": 313,
      "y": 325,
      "id": 26
    },
    {
      "timestamp": "2018-01-14T14:46:35.229Z",
      "x": 642,
      "y": 234,
      "id": 27
    },
    {
      "timestamp": "2018-01-14T14:46:35.596Z",
      "x": 530,
      "y": 141,
      "id": 28
    },
    {
      "timestamp": "2018-01-14T14:46:35.723Z",
      "x": 486,
      "y": 147,
      "id": 29
    },
    {
      "timestamp": "2018-01-14T14:46:35.823Z",
      "x": 412,
      "y": 156,
      "id": 30
    },
    {
      "timestamp": "2018-01-14T14:46:35.947Z",
      "x": 359,
      "y": 177,
      "id": 31
    },
    {
      "timestamp": "2018-01-14T14:46:36.066Z",
      "x": 391,
      "y": 248,
      "id": 32
    },
    {
      "timestamp": "2018-01-14T14:46:36.207Z",
      "x": 482,
      "y": 290,
      "id": 33
    },
    {
      "timestamp": "2018-01-14T14:46:36.354Z",
      "x": 575,
      "y": 325,
      "id": 34
    },
    {
      "timestamp": "2018-01-14T14:46:36.837Z",
      "x": 508,
      "y": 330,
      "id": 35
    },
    {
      "timestamp": "2018-01-14T14:46:37.015Z",
      "x": 504,
      "y": 336,
      "id": 36
    },
    {
      "timestamp": "2018-01-14T14:46:37.390Z",
      "x": 623,
      "y": 446,
      "id": 37
    },
    {
      "timestamp": "2018-01-14T14:46:37.665Z",
      "x": 649,
      "y": 302,
      "id": 38
    },
    {
      "timestamp": "2018-01-14T14:46:37.845Z",
      "x": 482,
      "y": 227,
      "id": 39
    },
    {
      "timestamp": "2018-01-14T14:46:38.083Z",
      "x": 504,
      "y": 304,
      "id": 40
    },
    {
      "timestamp": "2018-01-14T14:46:38.803Z",
      "x": 515,
      "y": 340,
      "id": 41
    },
    {
      "timestamp": "2018-01-14T14:46:39.100Z",
      "x": 517,
      "y": 345,
      "id": 42
    },
    {
      "timestamp": "2018-01-14T14:46:39.307Z",
      "x": 490,
      "y": 335,
      "id": 43
    },
    {
      "timestamp": "2018-01-14T14:46:39.376Z",
      "x": 294,
      "y": 273,
      "id": 44
    },
    {
      "timestamp": "2018-01-14T14:46:39.538Z",
      "x": 388,
      "y": 338,
      "id": 45
    },
    {
      "timestamp": "2018-01-14T14:46:40.274Z",
      "x": 408,
      "y": 333,
      "id": 46
    },
    {
      "timestamp": "2018-01-14T14:46:40.728Z",
      "x": 634,
      "y": 431,
      "id": 47
    },
    {
      "timestamp": "2018-01-14T14:46:41.480Z",
      "x": 495,
      "y": 472,
      "id": 48
    },
    {
      "timestamp": "2018-01-14T14:46:41.660Z",
      "x": 494,
      "y": 470,
      "id": 49
    },
    {
      "timestamp": "2018-01-14T14:46:41.937Z",
      "x": 590,
      "y": 470,
      "id": 50
    },
    {
      "timestamp": "2018-01-14T14:46:42.259Z",
      "x": 313,
      "y": 390,
      "id": 51
    },
    {
      "timestamp": "2018-01-14T14:46:42.443Z",
      "x": 479,
      "y": 363,
      "id": 52
    },
    {
      "timestamp": "2018-01-14T14:46:43.002Z",
      "x": 615,
      "y": 530,
      "id": 53
    },
    {
      "timestamp": "2018-01-14T14:46:43.601Z",
      "x": 501,
      "y": 442,
      "id": 54
    },
    {
      "timestamp": "2018-01-14T14:47:23.757Z",
      "x": 133,
      "y": 328,
      "id": 55
    }
  ]
}